Workbook

Sheet Cover
A1: Company Valuation & Financial Intelligence
A3: Starter company | B3: Apple Inc. (AAPL)
A5: Workflow | B5: Python → clean financial data → analysis/forecast → DCF/comps/Monte Carlo → Excel dashboard

Sheet Assumptions
A1: Assumptions
A2: Input | B2: Value | C2: Notes
A3: Risk-free rate | B3: 0.043 | C3: Replace with a current market assumption
A4: Equity risk premium | B4: 0.055 | C4: Assumption
A5: Beta | B5: 1 | C5: Pull/verify from market-data source
A6: Cost of debt | B6: 0.045 | C6: Assumption
A7: Tax rate | B7: 0.16 | C7: Assumption
A8: Terminal growth | B8: 0.025 | C8: Should remain below WACC
A9: Revenue growth | B9: 0.06 | C9: Base case
A10: EBITDA margin | B10: 0.34 | C10: Base case
A11: CapEx / Revenue | B11: 0.035 | C11: Base case
A12: ΔNWC / Revenue | B12: 0.005 | C12: Base case
A13: D&A / Revenue | B13: 0.04 | C13: Base case

Sheet Historical
A1: Historical
A2: 2002 | D2: =IFERROR(C2/B2,"") | F2: =IFERROR(E2/B2,"")
A3: 2003 | D3: =IFERROR(C3/B3,"") | F3: =IFERROR(E3/B3,"")
A4: 2004 | D4: =IFERROR(C4/B4,"") | F4: =IFERROR(E4/B4,"")
A5: 2005 | D5: =IFERROR(C5/B5,"") | F5: =IFERROR(E5/B5,"")
A6: 2006 | D6: =IFERROR(C6/B6,"") | F6: =IFERROR(E6/B6,"")
A7: 2007 | D7: =IFERROR(C7/B7,"") | F7: =IFERROR(E7/B7,"")
A8: 2008 | D8: =IFERROR(C8/B8,"") | F8: =IFERROR(E8/B8,"")
A9: 2009 | D9: =IFERROR(C9/B9,"") | F9: =IFERROR(E9/B9,"")
A10: 2010 | D10: =IFERROR(C10/B10,"") | F10: =IFERROR(E10/B10,"")
A11: 2011 | D11: =IFERROR(C11/B11,"") | F11: =IFERROR(E11/B11,"")

Sheet Forecast
A1: Forecast
A2: Year 1 | C2: =Assumptions!$B$9 | D2: =B2*Assumptions!$B$10 | E2: =IFERROR(D2/B2,"") | F2: =B2*Assumptions!$B$13 | G2: =D2-F2 | H2: =MAX(0,G2*Assumptions!$B$7) | I2: =G2-H2 | J2: =B2*Assumptions!$B$11 | K2: =B2*Assumptions!$B$12 | L2: =I2+F2-J2-K2
A3: Year 2 | B3: =IF(B2="","",B2*(1+Assumptions!$B$9)) | C3: =Assumptions!$B$9 | D3: =B3*Assumptions!$B$10 | E3: =IFERROR(D3/B3,"") | F3: =B3*Assumptions!$B$13 | G3: =D3-F3 | H3: =MAX(0,G3*Assumptions!$B$7) | I3: =G3-H3 | J3: =B3*Assumptions!$B$11 | K3: =B3*Assumptions!$B$12 | L3: =I3+F3-J3-K3
A4: Year 3 | B4: =IF(B3="","",B3*(1+Assumptions!$B$9)) | C4: =Assumptions!$B$9 | D4: =B4*Assumptions!$B$10 | E4: =IFERROR(D4/B4,"") | F4: =B4*Assumptions!$B$13 | G4: =D4-F4 | H4: =MAX(0,G4*Assumptions!$B$7) | I4: =G4-H4 | J4: =B4*Assumptions!$B$11 | K4: =B4*Assumptions!$B$12 | L4: =I4+F4-J4-K4
A5: Year 4 | B5: =IF(B4="","",B4*(1+Assumptions!$B$9)) | C5: =Assumptions!$B$9 | D5: =B5*Assumptions!$B$10 | E5: =IFERROR(D5/B5,"") | F5: =B5*Assumptions!$B$13 | G5: =D5-F5 | H5: =MAX(0,G5*Assumptions!$B$7) | I5: =G5-H5 | J5: =B5*Assumptions!$B$11 | K5: =B5*Assumptions!$B$12 | L5: =I5+F5-J5-K5
A6: Year 5 | B6: =IF(B5="","",B5*(1+Assumptions!$B$9)) | C6: =Assumptions!$B$9 | D6: =B6*Assumptions!$B$10 | E6: =IFERROR(D6/B6,"") | F6: =B6*Assumptions!$B$13 | G6: =D6-F6 | H6: =MAX(0,G6*Assumptions!$B$7) | I6: =G6-H6 | J6: =B6*Assumptions!$B$11 | K6: =B6*Assumptions!$B$12 | L6: =I6+F6-J6-K6

Sheet DCF
A1: DCF
A2: DCF Metric | B2: Value
A3: Cost of Equity | B3: =Assumptions!B4+Assumptions!B5*Assumptions!B6
A4: WACC | B4: =B2
A5: Terminal Growth | B5: =Assumptions!B8
A6: PV of Explicit FCF
A7: Terminal Value
A8: PV of Terminal Value
A9: Enterprise Value
A10: Net Debt
A11: Equity Value

Sheet Comps
A1: Comps

Sheet Sensitivity
A1: Sensitivity

Sheet Dashboard
A1: Dashboard
